setup.py
aio_requests/__init__.py
aio_requests.egg-info/PKG-INFO
aio_requests.egg-info/SOURCES.txt
aio_requests.egg-info/dependency_links.txt
aio_requests.egg-info/requires.txt
aio_requests.egg-info/top_level.txt